{
  "titles": [
    {
      "tl": "Update được rôi haha",
      "description": "Enter text here...",
      "id": "WfWljXw8-"
    },
    {
      "tl": "Trong mưa",
      "description": "Enter text here...",
      "id": "kchHgpk9S"
    },
    {
      "tl": "Tinh yeu mau nang",
      "description": "Enter text here...",
      "id": "a9TeKHoct"
    }
  ],
  "users": [
    {
      "isAdmin": "true",
      "name": "minhthao56",
      "email": "minhthao5648@gmail.com",
      "pass": "$2b$10$lzWdcF4akYvW0hygroeOXu8uqB8Bb4LyLGfkA8ZNxGCkpd2z2oCPC",
      "id": "A0ym4j2gY",
      "wrongLoginCount": 1
    },
    {
      "isAdmin": "false",
      "name": "Bích Diệu",
      "email": "dieu@mail.com",
      "pass": "$2b$10$H/JsGSkr8PJvROVeiW58eOkDS0iaJF3Apx9sUQWP.4AkUf0PGLbbu",
      "id": "6IloE2BM6",
      "wrongLoginCount": 1
    },
    {
      "isAdmin": "false",
      "wrongLoginCount": 1,
      "name": "Thịnh",
      "email": "thinh@mail.com",
      "pass": "$2b$10$mraR8AMnwKQP5NdWEvdLLOUCUynLAEdXCNOutix2qJ638LpCH2EL2",
      "id": "NwiUxkhJc"
    }
  ],
  "trans": [
    {
      "bookId": "WfWljXw8-",
      "userId": "-9KSGXUKw",
      "timeb": "18 giờ 45 phút ,  Ngày 13 Tháng 5 Năm 2020",
      "isComplete": "false",
      "id": "IH1QGVtrC"
    },
    {
      "bookId": "kchHgpk9S",
      "userId": "-9KSGXUKw",
      "timeb": "18 giờ 45 phút ,  Ngày 13 Tháng 5 Năm 2020",
      "isComplete": "false",
      "id": "euEXW4LH5"
    },
    {
      "bookId": "kchHgpk9S",
      "userId": "YH27ddlRC",
      "timeb": "18 giờ 47 phút ,  Ngày 13 Tháng 5 Năm 2020",
      "isComplete": "false",
      "id": "rCHqEaN_p"
    }
  ]
}